docs/conf.py
examples/async_usage.py
examples/basic_usage.py
examples/configuration.py
examples/error_handling.py
examples/init.py
exceptions/__init__.py
exceptions/authentication.py
exceptions/base.py
exceptions/network.py
exceptions/validation.py
models/__init__.py
models/common/__init__.py
models/common/api_response.py
models/common/error_details.py
models/request/__init__.py
models/request/api_key.py
models/request/auth.py
models/request/compound_interest.py
models/request/investment_returns.py
models/request/loan_calculation.py
models/response/__init__.py
models/response/api_key.py
models/response/auth.py
models/response/compound_interest.py
models/response/investment_returns.py
models/response/loan_calculation.py
models/response/plan.py
services/__init__.py
services/auth_service.py
services/http_service.py
services/validation_service.py
utils/__init__.py
utils/constants.py
utils/decorators.py
utils/json_utils.py
xfinance_sdk/__init__.py
xfinance_sdk/client.py
xfinance_sdk/init.py
xfinance_sdk/py.typed
xfinance_sdk/config/__init__.py
xfinance_sdk/config/retry_config.py
xfinance_sdk/config/settings.py
xfinance_python_sdk-1.0.5.dist-info/METADATA
xfinance_python_sdk-1.0.5.dist-info/WHEEL
xfinance_python_sdk-1.0.5.dist-info/top_level.txt
xfinance_python_sdk-1.0.5.dist-info/RECORD
