Metadata-Version: 2.4
Name: xfinance-python-sdk
Version: 1.0.5
Summary: Official Python SDK for X-Finance API
Author-email: Nestor Martourez <nestorabiawuh@gmail.com>
License: MIT
Project-URL: Homepage, https://github.com/martourez21/xfinance-python-sdk
Project-URL: Documentation, https://martourez21.github.io/xfinance-python-sdk/
Project-URL: Repository, https://github.com/martourez21/xfinance-python-sdk
Project-URL: Issues, https://github.com/martourez21/xfinance-python-sdk/issues
Classifier: Development Status :: 5 - Production/Stable
Classifier: Intended Audience :: Developers
Classifier: License :: OSI Approved :: MIT License
Classifier: Operating System :: OS Independent
Classifier: Programming Language :: Python :: 3
Classifier: Programming Language :: Python :: 3.8
Classifier: Programming Language :: Python :: 3.9
Classifier: Programming Language :: Python :: 3.10
Classifier: Programming Language :: Python :: 3.11
Classifier: Programming Language :: Python :: 3.12
Classifier: Topic :: Office/Business :: Financial
Classifier: Topic :: Software Development :: Libraries :: Python Modules
Requires-Python: >=3.8
Requires-Dist: requests>=2.28.0
Requires-Dist: pydantic>=1.10.0
Requires-Dist: aiohttp>=3.8.0
Requires-Dist: python-dotenv>=0.19.0
Provides-Extra: dev
Requires-Dist: pytest>=7.0.0; extra == "dev"
Requires-Dist: pytest-cov>=4.0.0; extra == "dev"
Requires-Dist: pytest-mock>=3.10.0; extra == "dev"
Requires-Dist: black>=23.0.0; extra == "dev"
Requires-Dist: isort>=5.12.0; extra == "dev"
Requires-Dist: flake8>=6.0.0; extra == "dev"
Requires-Dist: mypy>=1.0.0; extra == "dev"
Requires-Dist: pre-commit>=3.0.0; extra == "dev"
Requires-Dist: tox>=4.0.0; extra == "dev"
Provides-Extra: docs
Requires-Dist: sphinx>=6.0.0; extra == "docs"
Requires-Dist: sphinx-rtd-theme>=1.2.0; extra == "docs"
Requires-Dist: sphinx-autodoc-typehints>=1.20.0; extra == "docs"
Provides-Extra: async
Requires-Dist: aiohttp>=3.8.0; extra == "async"
